koli/__init__.py
koli/en.py
koli/sk.py
zen_of_koli-0.0.8.dist-info/LICENSE
zen_of_koli-0.0.8.dist-info/METADATA
zen_of_koli-0.0.8.dist-info/WHEEL
zen_of_koli-0.0.8.dist-info/top_level.txt
zen_of_koli-0.0.8.dist-info/RECORD
