Metadata-Version: 2.1
Name: zen-of-koli
Version: 0.0.8
Summary: Ultimite guide to life, python and all.
Home-page: https://github.com/maroshmka/zen-of-koli
Author: Mario Hunka
Author-email: hunka.mario@gmail.com
License: MIT
Platform: UNKNOWN
